src/torch-cpu-for-poetry/__init__.py
torch_cpu_for_poetry-2.5.1.dist-info/METADATA
torch_cpu_for_poetry-2.5.1.dist-info/WHEEL
torch_cpu_for_poetry-2.5.1.dist-info/licenses/LICENSE
torch_cpu_for_poetry-2.5.1.dist-info/RECORD
